zrb_extras/__init__.py
zrb_extras/__main__.py
zrb_extras/llm/tool/__init__.py
zrb_extras/llm/tool/factory.py
zrb_extras/llm/tool/google/__init__.py
zrb_extras/llm/tool/google/client.py
zrb_extras/llm/tool/google/default_config.py
zrb_extras/llm/tool/google/listen.py
zrb_extras/llm/tool/google/speak.py
zrb_extras/llm/tool/listen_wrapper.py
zrb_extras/llm/tool/openai/__init__.py
zrb_extras/llm/tool/openai/client.py
zrb_extras/llm/tool/openai/default_config.py
zrb_extras/llm/tool/openai/listen.py
zrb_extras/llm/tool/openai/speak.py
zrb_extras/llm/tool/pyttsx3/__init__.py
zrb_extras/llm/tool/pyttsx3/speak.py
zrb_extras/llm/tool/sound_classifier.py
zrb_extras/llm/tool/termux/__init__.py
zrb_extras/llm/tool/termux/default_config.py
zrb_extras/llm/tool/termux/listen.py
zrb_extras/llm/tool/termux/speak.py
zrb_extras/llm/tool/vad.py
zrb_extras/llm/tool/vosk/__init__.py
zrb_extras/llm/tool/vosk/default_config.py
zrb_extras/llm/tool/vosk/listen.py
zrb_extras/llm/tool/youtube/__init__.py
zrb_extras/llm/tool/youtube/transcript.py
zrb_extras-1.0.0.dist-info/METADATA
zrb_extras-1.0.0.dist-info/WHEEL
zrb_extras-1.0.0.dist-info/RECORD
