Metadata-Version: 2.4
Name: zrb-extras
Version: 1.0.0
Summary: Collection of Zrb additional utilities
License: AGPL-3.0-or-later
Author: Go Frendi Gunawan
Author-email: gofrendiasgard@gmail.com
Requires-Python: >=3.11.0,<3.14
Classifier: License :: OSI Approved :: GNU Affero General Public License v3 or later (AGPLv3+)
Classifier: Programming Language :: Python :: 3
Classifier: Programming Language :: Python :: 3.11
Classifier: Programming Language :: Python :: 3.12
Classifier: Programming Language :: Python :: 3.13
Provides-Extra: all
Provides-Extra: google-genai
Provides-Extra: openai
Provides-Extra: vosk
Provides-Extra: youtube
Requires-Dist: google-genai (>=1.32.0,<2.0.0) ; extra == "google-genai" or extra == "all"
Requires-Dist: numpy (>=2.3.2,<3.0.0) ; extra == "openai" or extra == "google-genai" or extra == "vosk" or extra == "all"
Requires-Dist: openai (>=2.14.0,<3.0.0) ; extra == "openai" or extra == "all"
Requires-Dist: pyttsx3 (>=2.99,<3.0) ; extra == "vosk" or extra == "all"
Requires-Dist: sounddevice (>=0.5.2,<0.6.0) ; extra == "openai" or extra == "google-genai" or extra == "vosk" or extra == "all"
Requires-Dist: soundfile (>=0.13.1,<0.14.0) ; extra == "openai" or extra == "google-genai" or extra == "all"
Requires-Dist: vosk (>=0.3.45,<0.4.0) ; extra == "vosk" or extra == "all"
Requires-Dist: youtube-transcript-api (>=0.6.3,<0.7.0) ; extra == "youtube" or extra == "all"
Requires-Dist: zrb (>=1.21.2)
Project-URL: Documentation, https://github.com/goFrendiAsgard/zrb-extras
Project-URL: Homepage, https://github.com/goFrendiAsgard/zrb-extras
Project-URL: Repository, https://github.com/goFrendiAsgard/zrb-extras
